nbit_mux.v
`timescale 1ps/1ps
module mux_n_1 #(
  parameter N = 8  
)(
  input  [8*N-1:0] inputs,     
  input  [$clog2(N)-1:0] sel,  
  output reg [7:0] d_out      
);

always @(*) begin
  d_out = inputs[sel*8 +: 8];  
end

endmodule

nbit_mux_tb.v
`timescale 1ps/1ps
module mux_n_1_tb;

  parameter N = 8;

  reg  [8*N-1:0] inputs;
  reg  [$clog2(N)-1:0] sel;
  wire [7:0] d_out;

  integer i;

  mux_n_1 #(.N(N)) uut (
    .inputs(inputs),
    .sel(sel),
    .d_out(d_out)
  );

  initial begin
    $dumpfile("mux_n_1.vcd");
    $dumpvars(0, mux_n_1_tb);
    $monitor("Time = %0t | sel = %0d | d_out = %h", $time, sel, d_out);

    
    for (i = 0; i < N; i = i + 1)
      inputs[i*8 +: 8] = (i+1) * 8'h11; 

    
    for (i = 0; i < N; i = i + 1) begin
      sel = i;
      #10;
    end

    $finish;
  end

endmodule

mux_n_1.vcd
$date
	Sun Jun 28 22:39:20 2026
$end
$version
	Icarus Verilog
$end
$timescale
	1ps
$end
$scope module mux_n_1_tb $end
$var wire 8 ! d_out [7:0] $end
$var reg 64 " inputs [63:0] $end
$var reg 3 # sel [2:0] $end
$var integer 32 $ i [31:0] $end
$scope module uut $end
$var wire 64 % inputs [63:0] $end
$var wire 3 & sel [2:0] $end
$var reg 8 ' d_out [7:0] $end
$upscope $end
$upscope $end
$enddefinitions $end
#0
$dumpvars
b10001 '
b0 &
b1000100001110111011001100101010101000100001100110010001000010001 %
b0 $
b0 #
b1000100001110111011001100101010101000100001100110010001000010001 "
b10001 !
$end
#10
b100010 !
b100010 '
b1 #
b1 &
b1 $
#20
b110011 !
b110011 '
b10 #
b10 &
b10 $
#30
b1000100 !
b1000100 '
b11 #
b11 &
b11 $
#40
b1010101 !
b1010101 '
b100 #
b100 &
b100 $
#50
b1100110 !
b1100110 '
b101 #
b101 &
b101 $
#60
b1110111 !
b1110111 '
b110 #
b110 &
b110 $
#70
b10001000 !
b10001000 '
b111 #
b111 &
b111 $
#80
b1000 $
